[
  { "id": "unit2-1", "english": "accent (n)", "hebrew": "מבטא", "successCount": 0 },
  { "id": "unit2-2", "english": "accompany (v)", "hebrew": "ללוות", "successCount": 0 },
  { "id": "unit2-3", "english": "accurate (adj)", "hebrew": "מדויק", "successCount": 0 },
  { "id": "unit2-4", "english": "achievement (n)", "hebrew": "הישג", "successCount": 0 },
  { "id": "unit2-5", "english": "actor (n)", "hebrew": "שחקן", "successCount": 0 },
  { "id": "unit2-6", "english": "actually (adv)", "hebrew": "למעשה / בעצם", "successCount": 0 },
  { "id": "unit2-7", "english": "afraid (adj)", "hebrew": "מפחד", "successCount": 0 },
  { "id": "unit2-8", "english": "airport (n)", "hebrew": "נמל תעופה", "successCount": 0 },
  { "id": "unit2-9", "english": "alter (v)", "hebrew": "לשנות", "successCount": 0 },
  { "id": "unit2-10", "english": "appreciate (v)", "hebrew": "להעריך", "successCount": 0 },
  { "id": "unit2-11", "english": "basic (adj)", "hebrew": "בסיסי", "successCount": 0 },
  { "id": "unit2-12", "english": "behave (v)", "hebrew": "להתנהג", "successCount": 0 },
  { "id": "unit2-13", "english": "camera (n)", "hebrew": "מצלמה", "successCount": 0 },
  { "id": "unit2-14", "english": "chat (v)", "hebrew": "לשוחח בצ'אט", "successCount": 0 },
  { "id": "unit2-15", "english": "childhood (n)", "hebrew": "ילדות", "successCount": 0 },
  { "id": "unit2-16", "english": "contact (v)", "hebrew": "ליצור קשר", "successCount": 0 },
  { "id": "unit2-17", "english": "detail (n)", "hebrew": "פרט", "successCount": 0 },
  { "id": "unit2-18", "english": "each other", "hebrew": "זה את זה", "successCount": 0 },
  { "id": "unit2-19", "english": "emotional (adj)", "hebrew": "רגשי", "successCount": 0 },
  { "id": "unit2-20", "english": "exactly (adv)", "hebrew": "בדיוק", "successCount": 0 },
  { "id": "unit2-21", "english": "expert (adv/n)", "hebrew": "מומחה", "successCount": 0 },
  { "id": "unit2-22", "english": "get along with", "hebrew": "להסתדר עם", "successCount": 0 },
  { "id": "unit2-23", "english": "gloves (n)", "hebrew": "כפפות", "successCount": 0 },
  { "id": "unit2-24", "english": "hairdryer (n)", "hebrew": "מייבש שיער", "successCount": 0 },
  { "id": "unit2-25", "english": "handbag (n)", "hebrew": "תיק יד", "successCount": 0 },
  { "id": "unit2-26", "english": "horrible (adj)", "hebrew": "נורא", "successCount": 0 },
  { "id": "unit2-27", "english": "huge (adj)", "hebrew": "ענק", "successCount": 0 },
  { "id": "unit2-28", "english": "minor (adj)", "hebrew": "קטן", "successCount": 0 },
  { "id": "unit2-29", "english": "movie theater (n)", "hebrew": "קולנוע", "successCount": 0 },
  { "id": "unit2-30", "english": "operate (v)", "hebrew": "לפעול / להפעיל", "successCount": 0 },
  { "id": "unit2-31", "english": "pleased (adj)", "hebrew": "מרוצה", "successCount": 0 },
  { "id": "unit2-32", "english": "police station (n)", "hebrew": "תחנת משטרה", "successCount": 0 },
  { "id": "unit2-33", "english": "railway station (n)", "hebrew": "תחנת רכבת", "successCount": 0 },
  { "id": "unit2-34", "english": "record (v)", "hebrew": "להקליט", "successCount": 0 },
  { "id": "unit2-35", "english": "research (n)", "hebrew": "מחקר", "successCount": 0 },
  { "id": "unit2-36", "english": "seaside (n)", "hebrew": "שפת הים", "successCount": 0 },
  { "id": "unit2-37", "english": "significant (adj)", "hebrew": "משמעותי", "successCount": 0 },
  { "id": "unit2-38", "english": "southern (adj)", "hebrew": "דרומי", "successCount": 0 },
  { "id": "unit2-39", "english": "spaceship (n)", "hebrew": "חללית", "successCount": 0 },
  { "id": "unit2-40", "english": "surprise (v)", "hebrew": "להפתיע", "successCount": 0 },
  { "id": "unit2-41", "english": "swimming pool (n)", "hebrew": "בריכת שחייה", "successCount": 0 },
  { "id": "unit2-42", "english": "technology (n)", "hebrew": "טכנולוגיה", "successCount": 0 },
  { "id": "unit2-43", "english": "traffic jam (n)", "hebrew": "פקק תנועה", "successCount": 0 },

  { "id": "unit2-44", "english": "afford (v)", "hebrew": "להרשות לעצמך (כלכלית)", "successCount": 0 },
  { "id": "unit2-45", "english": "apologize (v)", "hebrew": "להתנצל", "successCount": 0 },
  { "id": "unit2-46", "english": "be responsible for", "hebrew": "להיות אחראי ל-", "successCount": 0 },
  { "id": "unit2-47", "english": "blame (v)", "hebrew": "להאשים", "successCount": 0 },
  { "id": "unit2-48", "english": "condition (n)", "hebrew": "מצב / תנאי", "successCount": 0 },
  { "id": "unit2-49", "english": "contract (n)", "hebrew": "חוזה", "successCount": 0 },
  { "id": "unit2-50", "english": "convince (v)", "hebrew": "לשכנע", "successCount": 0 },
  { "id": "unit2-51", "english": "director (n)", "hebrew": "במאי", "successCount": 0 },
  { "id": "unit2-52", "english": "doubt (n)", "hebrew": "ספק", "successCount": 0 },
  { "id": "unit2-53", "english": "encourage (v)", "hebrew": "לעודד", "successCount": 0 },
  { "id": "unit2-54", "english": "enemy (n)", "hebrew": "אויב", "successCount": 0 },
  { "id": "unit2-55", "english": "even (adv)", "hebrew": "אפילו", "successCount": 0 },
  { "id": "unit2-56", "english": "extremely (adv)", "hebrew": "באופן קיצוני", "successCount": 0 },
  { "id": "unit2-57", "english": "fight (n)", "hebrew": "ריב", "successCount": 0 },
  { "id": "unit2-58", "english": "hug (v)", "hebrew": "לחבק", "successCount": 0 },
  { "id": "unit2-59", "english": "hunger (n)", "hebrew": "רעב", "successCount": 0 },
  { "id": "unit2-60", "english": "invent (v)", "hebrew": "להמציא", "successCount": 0 },
  { "id": "unit2-61", "english": "lie (n)", "hebrew": "שקר", "successCount": 0 },
  { "id": "unit2-62", "english": "make up", "hebrew": "להמציא (סיפור/תירוץ)", "successCount": 0 },
  { "id": "unit2-63", "english": "minister (n)", "hebrew": "שר (בממשלה)", "successCount": 0 },
  { "id": "unit2-64", "english": "opening (n)", "hebrew": "פתיחה", "successCount": 0 },
  { "id": "unit2-65", "english": "otherwise", "hebrew": "אחרת", "successCount": 0 },
  { "id": "unit2-66", "english": "play (n)", "hebrew": "מחזה", "successCount": 0 },
  { "id": "unit2-67", "english": "president (n)", "hebrew": "נשיא", "successCount": 0 },
  { "id": "unit2-68", "english": "role (n)", "hebrew": "תפקיד", "successCount": 0 },
  { "id": "unit2-69", "english": "stage (n)", "hebrew": "במה", "successCount": 0 },
  { "id": "unit2-70", "english": "star (n)", "hebrew": "כוכב", "successCount": 0 },
  { "id": "unit2-71", "english": "tax (n)", "hebrew": "מס", "successCount": 0 },
  { "id": "unit2-72", "english": "tell (a story) (v)", "hebrew": "לספר (סיפור)", "successCount": 0 },
  { "id": "unit2-73", "english": "terrible (adj)", "hebrew": "נורא", "successCount": 0 },
  { "id": "unit2-74", "english": "title (n)", "hebrew": "כותרת", "successCount": 0 },
  { "id": "unit2-75", "english": "truth (n)", "hebrew": "אמת", "successCount": 0 },
  { "id": "unit2-76", "english": "twice (adv)", "hebrew": "פעמיים", "successCount": 0 },
  { "id": "unit2-77", "english": "upset (adj)", "hebrew": "עצוב / כועס", "successCount": 0 },
  { "id": "unit2-78", "english": "a shame", "hebrew": "חבל", "successCount": 0 },
  { "id": "unit2-79", "english": "be crazy about", "hebrew": "\"משוגע על\" / \"מת על\"", "successCount": 0 },
  { "id": "unit2-80", "english": "book (v)", "hebrew": "להזמין (מקום/כרטיס)", "successCount": 0 },
  { "id": "unit2-81", "english": "can't wait", "hebrew": "לא יכול לחכות", "successCount": 0 },
  { "id": "unit2-82", "english": "in time", "hebrew": "בזמן", "successCount": 0 },
  { "id": "unit2-83", "english": "Oh no!", "hebrew": "אוי לא!", "successCount": 0 },
  { "id": "unit2-84", "english": "online (adv)", "hebrew": "מחובר / באינטרנט", "successCount": 0 },
  { "id": "unit2-85", "english": "pick up", "hebrew": "לאסוף (מישהו/משהו)", "successCount": 0 },
  { "id": "unit2-86", "english": "sound(s) good/interesting/strange", "hebrew": "נשמע טוב / מעניין / מוזר", "successCount": 0 }
]
